beautyroot/__init__.py
beautyroot/main.py
rumihelling-0.0.1.dist-info/LICENSE
rumihelling-0.0.1.dist-info/METADATA
rumihelling-0.0.1.dist-info/WHEEL
rumihelling-0.0.1.dist-info/top_level.txt
rumihelling-0.0.1.dist-info/RECORD
