Metadata-Version: 2.1
Name: rumihelling
Version: 0.0.1
Summary: A small package to build colorful python code
Home-page: https://github.com/pypa/sampleproject
Author: rumisoft
Author-email: devopswithbrad@gmail.com
Project-URL: Bug Tracker, https://github.com/pypa/sampleproject/issues
Classifier: Programming Language :: Python :: 3
Classifier: License :: OSI Approved :: MIT License
Classifier: Operating System :: OS Independent
Requires-Python: >=3.6
License-File: LICENSE
